unlok_next/__init__.py
unlok_next/arkitekt.py
unlok_next/errors.py
unlok_next/funcs.py
unlok_next/rath.py
unlok_next/rekuest.py
unlok_next/scalars.py
unlok_next/unlok.py
unlok_next/api/project.json
unlok_next/api/schema.graphql
unlok_next/api/schema.py
unlok_next/bloks/service.py
unlok_next-1.3.0.dist-info/METADATA
unlok_next-1.3.0.dist-info/WHEEL
unlok_next-1.3.0.dist-info/RECORD
