Metadata-Version: 2.4
Name: unlok-next
Version: 1.3.0
Author-email: jhnnsrs <jhnnsrs@gmail.com>
Requires-Python: >=3.11
Requires-Dist: dokker>=2
Requires-Dist: rath>=3.7
Requires-Dist: websockets>=15.0.1
